gooise/__init__.py
gooise/__main__.py
gooise/condition.py
gooise/driver.py
gooise/exception.py
gooise/flow.py
gooise/locator.py
gooise/searcher.py
gooise/uploader.py
gooise-2020.7.18.8.data/data/LICENSE
gooise-2020.7.18.8.dist-info/LICENSE
gooise-2020.7.18.8.dist-info/METADATA
gooise-2020.7.18.8.dist-info/WHEEL
gooise-2020.7.18.8.dist-info/entry_points.txt
gooise-2020.7.18.8.dist-info/top_level.txt
gooise-2020.7.18.8.dist-info/RECORD
