Metadata-Version: 2.1
Name: gooise
Version: 2020.7.18.8
Summary: Search for similar images on Google using Selenium
Home-page: https://gitlab.com/scpketer/gooise
Author: scpketer
Author-email: scpketer@protonmail.ch
License: GNU GPLv3
Project-URL: Source, https://gitlab.com/scpketer/gooise
Project-URL: Tracker, https://gitlab.com/scpketer/gooise/issues
Keywords: google,image,search,automation,selenium
Platform: UNKNOWN
Classifier: Development Status :: 4 - Beta
Classifier: Environment :: Console
Classifier: Environment :: Web Environment
Classifier: Intended Audience :: End Users/Desktop
Classifier: License :: OSI Approved :: GNU General Public License v3 (GPLv3)
Classifier: Operating System :: OS Independent
Classifier: Topic :: Internet :: WWW/HTTP :: Indexing/Search
Requires-Dist: selenium (==3.141.0)
Requires-Dist: requests (==2.24.0)
